COPYING.txt
MANIFEST.in
README.txt
setup.cfg
setup.py
couchable/__init__.py
couchable/core.py
couchable.egg-info/PKG-INFO
couchable.egg-info/SOURCES.txt
couchable.egg-info/dependency_links.txt
couchable.egg-info/requires.txt
couchable.egg-info/top_level.txt