Metadata-Version: 1.0
Name: couchable
Version: 0.3.4a1
Summary: Allows arbitrary python objects to be stored in CouchDB, while keeping the resulting CouchDB document as "natural" as possible.
Home-page: http://github.com/wickedgrey/couchable
Author: Eli Stevens
Author-email: wickedgrey@gmail.com
License: UNKNOWN
Platform: UNKNOWN
Classifier: Development Status :: 4 - Beta
Classifier: Intended Audience :: Developers
Classifier: License :: OSI Approved :: MIT License
Classifier: Natural Language :: English
Classifier: Programming Language :: Python :: 2.7
Classifier: Topic :: Database :: Front-Ends
